octvi/__init__.py
octvi/_version.py
octvi/array.py
octvi/command_line.py
octvi/config.py
octvi/exceptions.py
octvi/extract.py
octvi/url.py
octvi-2.1.0.dist-info/LICENSE
octvi-2.1.0.dist-info/METADATA
octvi-2.1.0.dist-info/WHEEL
octvi-2.1.0.dist-info/entry_points.txt
octvi-2.1.0.dist-info/top_level.txt
octvi-2.1.0.dist-info/RECORD
