Metadata-Version: 2.1
Name: octvi
Version: 2.1.0
Summary: MODIS 8-day NDVI Downloader
Home-page: https://github.com/fdfoneill/octvi
Author: F. Dan O'Neill
Author-email: fdfoneill@gmail.com
License: MIT
Platform: UNKNOWN
Classifier: License :: OSI Approved :: MIT License
Classifier: Programming Language :: Python :: 3
Classifier: Programming Language :: Python :: 3.7
Requires-Dist: numpy (>=1.18)
Requires-Dist: h5py
Requires-Dist: gdal
